{
    "boxShadow": "{{appsmith.theme.boxShadow.appBoxShadow}}",
    "widgetName": "data_table",
    "onSort": "{{FindQuery.run()}}",
    "columnOrder": [
        "revenue1",
        "imdb_id1",
        "release_date1",
        "genres1",
        "vote_average1",
        "tagline1",
        "_id1",
        "title1",
        "vote_count1",
        "poster_path1",
        "homepage1",
        "status1",
        "customColumn1"
    ],
    "dynamicPropertyPathList": [
        {"key": "onPageChange"},
        {"key": "primaryColumns.customColumn1.borderRadius"},
        {"key": "tableData"}
    ],
    "isVisibleDownload": true,
    "topRow": 7,
    "bottomRow": 86,
    "parentRowSpace": 10,
    "onPageChange": "{{FindQuery.run()}}",
    "isSortable": true,
    "type": "TABLE_WIDGET_V2",
    "animateLoading": true,
    "parentColumnSpace": 1,
    "dynamicTriggerPathList": [
        {"key": "onPageChange"},
        {"key": "primaryColumns.customColumn1.onClick"},
        {"key": "onSearchTextChanged"},
        {"key": "onSort"}
    ],
    "dynamicBindingPathList": [
        {"key": "primaryColumns.customColumn1.buttonLabel"},
        {"key": "accentColor"},
        {"key": "borderRadius"},
        {"key": "boxShadow"},
        {"key": "primaryColumns.customColumn1.borderRadius"},
        {"key": "tableData"},
        {"key": "derivedColumns.customColumn1.boxShadow"},
        {"key": "primaryColumns.customColumn1.boxShadow"},
        {"key": "derivedColumns.customColumn1.borderRadius"},
        {"key": "derivedColumns.customColumn1.buttonColor"},
        {"key": "primaryColumns.customColumn1.buttonColor"},
        {"key": "primaryColumns.customColumn1.computedValue"},
        {"key": "derivedColumns.customColumn1.computedValue"},
        {"key": "primaryColumns.revenue1.computedValue"},
        {"key": "primaryColumns.imdb_id1.computedValue"},
        {"key": "primaryColumns.release_date1.computedValue"},
        {"key": "primaryColumns.genres1.computedValue"},
        {"key": "primaryColumns.vote_average1.computedValue"},
        {"key": "primaryColumns.tagline1.computedValue"},
        {"key": "primaryColumns._id1.computedValue"},
        {"key": "primaryColumns.title1.computedValue"},
        {"key": "primaryColumns.vote_count1.computedValue"},
        {"key": "primaryColumns.poster_path1.computedValue"},
        {"key": "primaryColumns.homepage1.computedValue"},
        {"key": "primaryColumns.status1.computedValue"}
    ],
    "leftColumn": 1,
    "primaryColumns": {
        "imdb_id1": {
            "computedValue": "{{data_table.processedTableData.map((currentRow, currentIndex) => ( currentRow[\"imdb_id\"]))}}",
            "isEditable": false,
            "notation": "standard",
            "alias": "imdb_id",
            "enableSort": true,
            "isSaveVisible": true,
            "id": "imdb_id1",
            "isDisabled": false,
            "allowSameOptionsInNewRow": true,
            "validation": {},
            "isCellVisible": true,
            "isDerived": false,
            "textSize": "0.875rem",
            "allowCellWrapping": false,
            "index": 1,
            "isDiscardVisible": true,
            "isVisible": true,
            "label": "imdb_id",
            "fontStyle": "",
            "textColor": "",
            "columnType": "text",
            "thousandSeparator": true,
            "horizontalAlignment": "LEFT",
            "isCellEditable": false,
            "decimals": 0,
            "width": 150,
            "enableFilter": true,
            "sticky": "",
            "originalId": "imdb_id",
            "currencyCode": "USD",
            "cellBackground": "",
            "verticalAlignment": "CENTER"
        },
        "vote_average1": {
            "computedValue": "{{data_table.processedTableData.map((currentRow, currentIndex) => ( currentRow[\"vote_average\"]))}}",
            "isEditable": false,
            "notation": "standard",
            "alias": "vote_average",
            "enableSort": true,
            "isSaveVisible": true,
            "id": "vote_average1",
            "isDisabled": false,
            "allowSameOptionsInNewRow": true,
            "validation": {},
            "isCellVisible": true,
            "isDerived": false,
            "textSize": "0.875rem",
            "allowCellWrapping": false,
            "index": 4,
            "isDiscardVisible": true,
            "isVisible": true,
            "label": "vote_average",
            "fontStyle": "",
            "textColor": "",
            "columnType": "number",
            "thousandSeparator": true,
            "horizontalAlignment": "LEFT",
            "isCellEditable": false,
            "decimals": 0,
            "width": 150,
            "enableFilter": true,
            "sticky": "",
            "originalId": "vote_average",
            "currencyCode": "USD",
            "cellBackground": "",
            "verticalAlignment": "CENTER"
        },
        "tagline1": {
            "computedValue": "{{data_table.processedTableData.map((currentRow, currentIndex) => ( currentRow[\"tagline\"]))}}",
            "isEditable": false,
            "notation": "standard",
            "alias": "tagline",
            "enableSort": true,
            "isSaveVisible": true,
            "id": "tagline1",
            "isDisabled": false,
            "allowSameOptionsInNewRow": true,
            "validation": {},
            "isCellVisible": true,
            "isDerived": false,
            "textSize": "0.875rem",
            "allowCellWrapping": false,
            "index": 5,
            "isDiscardVisible": true,
            "isVisible": true,
            "label": "tagline",
            "fontStyle": "",
            "textColor": "",
            "columnType": "text",
            "thousandSeparator": true,
            "horizontalAlignment": "LEFT",
            "isCellEditable": false,
            "decimals": 0,
            "width": 150,
            "enableFilter": true,
            "sticky": "",
            "originalId": "tagline",
            "currencyCode": "USD",
            "cellBackground": "",
            "verticalAlignment": "CENTER"
        },
        "title1": {
            "computedValue": "{{data_table.processedTableData.map((currentRow, currentIndex) => ( currentRow[\"title\"]))}}",
            "isEditable": false,
            "notation": "standard",
            "alias": "title",
            "enableSort": true,
            "isSaveVisible": true,
            "id": "title1",
            "isDisabled": false,
            "allowSameOptionsInNewRow": true,
            "validation": {},
            "isCellVisible": true,
            "isDerived": false,
            "textSize": "0.875rem",
            "allowCellWrapping": false,
            "index": 7,
            "isDiscardVisible": true,
            "isVisible": true,
            "label": "title",
            "fontStyle": "",
            "textColor": "",
            "columnType": "text",
            "thousandSeparator": true,
            "horizontalAlignment": "LEFT",
            "isCellEditable": false,
            "decimals": 0,
            "width": 150,
            "enableFilter": true,
            "sticky": "",
            "originalId": "title",
            "currencyCode": "USD",
            "cellBackground": "",
            "verticalAlignment": "CENTER"
        },
        "poster_path1": {
            "computedValue": "{{data_table.processedTableData.map((currentRow, currentIndex) => ( currentRow[\"poster_path\"]))}}",
            "isEditable": false,
            "notation": "standard",
            "alias": "poster_path",
            "enableSort": true,
            "isSaveVisible": true,
            "id": "poster_path1",
            "isDisabled": false,
            "allowSameOptionsInNewRow": true,
            "validation": {},
            "isCellVisible": true,
            "isDerived": false,
            "textSize": "0.875rem",
            "allowCellWrapping": false,
            "index": 9,
            "isDiscardVisible": true,
            "isVisible": true,
            "label": "poster_path",
            "fontStyle": "",
            "textColor": "",
            "columnType": "text",
            "thousandSeparator": true,
            "horizontalAlignment": "LEFT",
            "isCellEditable": false,
            "decimals": 0,
            "width": 150,
            "enableFilter": true,
            "sticky": "",
            "originalId": "poster_path",
            "currencyCode": "USD",
            "cellBackground": "",
            "verticalAlignment": "CENTER"
        },
        "customColumn1": {
            "isCellVisible": true,
            "boxShadow": "{{data_table.processedTableData.map((currentRow, currentIndex) => ( \"none\"))}}",
            "isDerived": true,
            "computedValue": "{{data_table.processedTableData.map((currentRow, currentIndex) => ( currentRow.customColumn1))}}",
            "onClick": "{{showModal('Delete_Modal')}}",
            "textSize": "0.875rem",
            "buttonColor": "{{data_table.processedTableData.map((currentRow, currentIndex) => ( (appsmith.theme.colors.primaryColor)))}}",
            "iconName": "",
            "index": 7,
            "isVisible": true,
            "label": "Delete",
            "buttonLabel": "{{data_table.processedTableData.map((currentRow, currentIndex) => { return 'Delete'})}}",
            "columnType": "button",
            "horizontalAlignment": "LEFT",
            "borderRadius": "{{data_table.processedTableData.map((currentRow, currentIndex) => ( (appsmith.theme.borderRadius.appBorderRadius)))}}",
            "width": 150,
            "enableFilter": true,
            "sticky": "right",
            "enableSort": true,
            "id": "customColumn1",
            "isDisabled": false,
            "buttonLabelColor": "#FFFFFF",
            "verticalAlignment": "CENTER"
        },
        "homepage1": {
            "computedValue": "{{data_table.processedTableData.map((currentRow, currentIndex) => ( currentRow[\"homepage\"]))}}",
            "isEditable": false,
            "notation": "standard",
            "alias": "homepage",
            "enableSort": true,
            "isSaveVisible": true,
            "id": "homepage1",
            "isDisabled": false,
            "allowSameOptionsInNewRow": true,
            "validation": {},
            "isCellVisible": true,
            "isDerived": false,
            "textSize": "0.875rem",
            "allowCellWrapping": false,
            "index": 10,
            "isDiscardVisible": true,
            "isVisible": true,
            "label": "homepage",
            "fontStyle": "",
            "textColor": "",
            "columnType": "text",
            "thousandSeparator": true,
            "horizontalAlignment": "LEFT",
            "isCellEditable": false,
            "decimals": 0,
            "width": 150,
            "enableFilter": true,
            "sticky": "",
            "originalId": "homepage",
            "currencyCode": "USD",
            "cellBackground": "",
            "verticalAlignment": "CENTER"
        },
        "revenue1": {
            "computedValue": "{{data_table.processedTableData.map((currentRow, currentIndex) => ( currentRow[\"revenue\"]))}}",
            "isEditable": false,
            "notation": "standard",
            "alias": "revenue",
            "enableSort": true,
            "isSaveVisible": true,
            "id": "revenue1",
            "isDisabled": false,
            "allowSameOptionsInNewRow": true,
            "validation": {},
            "isCellVisible": true,
            "isDerived": false,
            "textSize": "0.875rem",
            "allowCellWrapping": false,
            "index": 0,
            "isDiscardVisible": true,
            "isVisible": true,
            "label": "revenue",
            "fontStyle": "",
            "textColor": "",
            "columnType": "number",
            "thousandSeparator": true,
            "horizontalAlignment": "LEFT",
            "isCellEditable": false,
            "decimals": 0,
            "width": 150,
            "enableFilter": true,
            "sticky": "",
            "originalId": "revenue",
            "currencyCode": "USD",
            "cellBackground": "",
            "verticalAlignment": "CENTER"
        },
        "release_date1": {
            "computedValue": "{{data_table.processedTableData.map((currentRow, currentIndex) => ( currentRow[\"release_date\"]))}}",
            "isEditable": false,
            "notation": "standard",
            "alias": "release_date",
            "enableSort": true,
            "isSaveVisible": true,
            "id": "release_date1",
            "isDisabled": false,
            "allowSameOptionsInNewRow": true,
            "validation": {},
            "isCellVisible": true,
            "isDerived": false,
            "textSize": "0.875rem",
            "allowCellWrapping": false,
            "index": 2,
            "isDiscardVisible": true,
            "isVisible": true,
            "label": "release_date",
            "fontStyle": "",
            "textColor": "",
            "columnType": "date",
            "thousandSeparator": true,
            "horizontalAlignment": "LEFT",
            "isCellEditable": false,
            "decimals": 0,
            "width": 150,
            "enableFilter": true,
            "sticky": "",
            "originalId": "release_date",
            "currencyCode": "USD",
            "cellBackground": "",
            "verticalAlignment": "CENTER"
        },
        "status1": {
            "computedValue": "{{data_table.processedTableData.map((currentRow, currentIndex) => ( currentRow[\"status\"]))}}",
            "isEditable": false,
            "notation": "standard",
            "alias": "status",
            "enableSort": true,
            "isSaveVisible": true,
            "id": "status1",
            "isDisabled": false,
            "allowSameOptionsInNewRow": true,
            "validation": {},
            "isCellVisible": true,
            "isDerived": false,
            "textSize": "0.875rem",
            "allowCellWrapping": false,
            "index": 11,
            "isDiscardVisible": true,
            "isVisible": true,
            "label": "status",
            "fontStyle": "",
            "textColor": "",
            "columnType": "text",
            "thousandSeparator": true,
            "horizontalAlignment": "LEFT",
            "isCellEditable": false,
            "decimals": 0,
            "width": 150,
            "enableFilter": true,
            "sticky": "",
            "originalId": "status",
            "currencyCode": "USD",
            "cellBackground": "",
            "verticalAlignment": "CENTER"
        },
        "vote_count1": {
            "computedValue": "{{data_table.processedTableData.map((currentRow, currentIndex) => ( currentRow[\"vote_count\"]))}}",
            "isEditable": false,
            "notation": "standard",
            "alias": "vote_count",
            "enableSort": true,
            "isSaveVisible": true,
            "id": "vote_count1",
            "isDisabled": false,
            "allowSameOptionsInNewRow": true,
            "validation": {},
            "isCellVisible": true,
            "isDerived": false,
            "textSize": "0.875rem",
            "allowCellWrapping": false,
            "index": 8,
            "isDiscardVisible": true,
            "isVisible": true,
            "label": "vote_count",
            "fontStyle": "",
            "textColor": "",
            "columnType": "number",
            "thousandSeparator": true,
            "horizontalAlignment": "LEFT",
            "isCellEditable": false,
            "decimals": 0,
            "width": 150,
            "enableFilter": true,
            "sticky": "",
            "originalId": "vote_count",
            "currencyCode": "USD",
            "cellBackground": "",
            "verticalAlignment": "CENTER"
        },
        "_id1": {
            "computedValue": "{{data_table.processedTableData.map((currentRow, currentIndex) => ( currentRow[\"_id\"]))}}",
            "isEditable": false,
            "notation": "standard",
            "alias": "_id",
            "enableSort": true,
            "isSaveVisible": true,
            "id": "_id1",
            "isDisabled": false,
            "allowSameOptionsInNewRow": true,
            "validation": {},
            "isCellVisible": true,
            "isDerived": false,
            "textSize": "0.875rem",
            "allowCellWrapping": false,
            "index": 6,
            "isDiscardVisible": true,
            "isVisible": true,
            "label": "_id",
            "fontStyle": "",
            "textColor": "",
            "columnType": "text",
            "thousandSeparator": true,
            "horizontalAlignment": "LEFT",
            "isCellEditable": false,
            "decimals": 0,
            "width": 150,
            "enableFilter": true,
            "sticky": "",
            "originalId": "_id",
            "currencyCode": "USD",
            "cellBackground": "",
            "verticalAlignment": "CENTER"
        },
        "genres1": {
            "computedValue": "{{data_table.processedTableData.map((currentRow, currentIndex) => ( currentRow[\"genres\"]))}}",
            "isEditable": false,
            "notation": "standard",
            "alias": "genres",
            "enableSort": true,
            "isSaveVisible": true,
            "id": "genres1",
            "isDisabled": false,
            "allowSameOptionsInNewRow": true,
            "validation": {},
            "isCellVisible": true,
            "isDerived": false,
            "textSize": "0.875rem",
            "allowCellWrapping": false,
            "index": 3,
            "isDiscardVisible": true,
            "isVisible": true,
            "label": "genres",
            "fontStyle": "",
            "textColor": "",
            "columnType": "text",
            "thousandSeparator": true,
            "horizontalAlignment": "LEFT",
            "isCellEditable": false,
            "decimals": 0,
            "width": 150,
            "enableFilter": true,
            "sticky": "",
            "originalId": "genres",
            "currencyCode": "USD",
            "cellBackground": "",
            "verticalAlignment": "CENTER"
        }
    },
    "delimiter": ",",
    "defaultSelectedRowIndex": "0",
    "derivedColumns": {"customColumn1": {
        "boxShadow": "{{data_table.processedTableData.map((currentRow, currentIndex) => ( \"none\"))}}",
        "isDerived": true,
        "computedValue": "{{data_table.processedTableData.map((currentRow, currentIndex) => ( currentRow.customColumn1))}}",
        "onClick": "{{DeleteQuery.run()}}",
        "textSize": "0.875rem",
        "buttonColor": "{{data_table.processedTableData.map((currentRow, currentIndex) => ( (appsmith.theme.colors.primaryColor)))}}",
        "buttonStyle": "#DD4B34",
        "index": 7,
        "isVisible": true,
        "label": "Delete",
        "buttonLabel": "{{data_table.processedTableData.map((currentRow, currentIndex) => { return 'Delete'})}}",
        "columnType": "button",
        "horizontalAlignment": "LEFT",
        "borderRadius": "{{data_table.processedTableData.map((currentRow, currentIndex) => ( (appsmith.theme.borderRadius.appBorderRadius)))}}",
        "width": 150,
        "enableFilter": true,
        "enableSort": true,
        "id": "customColumn1",
        "buttonLabelColor": "#FFFFFF",
        "verticalAlignment": "CENTER"
    }},
    "labelTextSize": "0.875rem",
    "rightColumn": 64,
    "textSize": "0.875rem",
    "widgetId": "m04j9ji345",
    "accentColor": "{{appsmith.theme.colors.primaryColor}}",
    "enableServerSideFiltering": false,
    "isVisibleFilters": true,
    "tableData": "{{FindQuery.data}}",
    "isVisible": "true",
    "label": "Data",
    "searchKey": "",
    "version": 3,
    "parentId": "59rw5mx0bq",
    "serverSidePaginationEnabled": true,
    "isLoading": false,
    "isVisibleCompactMode": true,
    "onSearchTextChanged": "{{FindQuery.run()}}",
    "horizontalAlignment": "LEFT",
    "isVisibleSearch": true,
    "childStylesheet": {
        "button": {
            "boxShadow": "none",
            "borderRadius": "{{appsmith.theme.borderRadius.appBorderRadius}}",
            "buttonColor": "{{appsmith.theme.colors.primaryColor}}"
        },
        "iconButton": {
            "boxShadow": "none",
            "borderRadius": "{{appsmith.theme.borderRadius.appBorderRadius}}",
            "menuColor": "{{appsmith.theme.colors.primaryColor}}"
        },
        "menuButton": {
            "boxShadow": "none",
            "borderRadius": "{{appsmith.theme.borderRadius.appBorderRadius}}",
            "menuColor": "{{appsmith.theme.colors.primaryColor}}"
        }
    },
    "borderRadius": "{{appsmith.theme.borderRadius.appBorderRadius}}",
    "isVisiblePagination": true,
    "columnUpdatedAt": 1704988361726,
    "primaryColumnId": "_id",
    "verticalAlignment": "CENTER",
    "columnSizeMap": {
        "task": 245,
        "deliveryAddress": 170,
        "step": 62,
        "id": 228,
        "status": 75
    }
}